HISTORY.md
MANIFEST.in
README.md
requirements.txt
setup.cfg
setup.py
data_steps/VERSION
data_steps/__init__.py
data_steps/__main__.py
data_steps/export.py
data_steps/single_frame.py
data_steps.egg-info/PKG-INFO
data_steps.egg-info/SOURCES.txt
data_steps.egg-info/dependency_links.txt
data_steps.egg-info/requires.txt
data_steps.egg-info/top_level.txt
data_steps/tests/__init__.py
data_steps/tests/test_datasteps.py
data_steps/tests/test_export.py
data_steps/tests/test_step.py
data_steps/tests/test_step_collection.py