Metadata-Version: 2.1
Name: data-steps
Version: 0.3.2
Summary: Simple tool for pandas data transformation
Home-page: https://github.com/KonradUdoHannes/data-steps
Author: Konrad Wölms
Author-email: konrad.woelms@gmail.com
License: MIT
Platform: UNKNOWN
Requires-Python: >=3.8
Provides-Extra: test
